BMIpsyTest/BMIpsyTest.py
BMIpsyTest-0.0.0.3.dist-info/METADATA
BMIpsyTest-0.0.0.3.dist-info/WHEEL
BMIpsyTest-0.0.0.3.dist-info/top_level.txt
BMIpsyTest-0.0.0.3.dist-info/RECORD
