Metadata-Version: 2.1
Name: BMIpsyTest
Version: 0.0.0.3
Summary: My First Test Package
Home-page: https://blog.naver.com/hulcheongi
Author: Seungyeon Park
Author-email: serpens994@gmail.com
License: MIT
Platform: UNKNOWN
Requires-Python: >=3
